lyrics_translator/__init__.py
lyrics_translator/console.py
lyrics_translator/core/lyrics.py
lyrics_translator/core/lyrics_translator.py
lyrics_translator/core/saver.py
lyrics_translator/core/translator.py
lyrics_translator/core/utils.py
lyrics_translator-0.4.0.dist-info/METADATA
lyrics_translator-0.4.0.dist-info/WHEEL
lyrics_translator-0.4.0.dist-info/entry_points.txt
lyrics_translator-0.4.0.dist-info/RECORD
