Metadata-Version: 2.1
Name: lyrics-translator
Version: 0.4.0
Summary: 🎵 LyricsTranslator - automated lyrics translation
Home-page: https://mauroluzzatto.github.io/lyrics-translator
License: MIT
Keywords: lyrics,translation
Author: Mauro Luzzatto
Author-email: mauroluzzatto@hotmail.com
Requires-Python: >=3.8,<4.0
Classifier: License :: OSI Approved :: MIT License
Classifier: Programming Language :: Python :: 3
Classifier: Programming Language :: Python :: 3.8
Classifier: Programming Language :: Python :: 3.9
Classifier: Programming Language :: Python :: 3.10
Classifier: Programming Language :: Python :: 3.11
Requires-Dist: click (>=8.1.3,<9.0.0)
Requires-Dist: lyricsgenius (>=3.0.1,<4.0.0)
Requires-Dist: python-docx (>=0.8.11,<0.9.0)
Requires-Dist: python-dotenv (>=0.20.0,<0.21.0)
Requires-Dist: sacremoses (>=0.0.53,<0.0.54)
Requires-Dist: sentencepiece (>=0.1.96,<0.2.0)
Requires-Dist: tqdm (>=4.64.1,<5.0.0)
Requires-Dist: transformers[torch] (>=4.20.1,<5.0.0)
Project-URL: Repository, https://github.com/MauroLuzzatto/lyrics-translator
